{
  "text": "ὄφεις γεννήματα ἐχιδνῶν, πῶς φύγητε ἀπὸ τῆς κρίσεως τῆς γεέννης;",
  "words": [
    {
      "position": 1,
      "text": "ὄφεις",
      "lemma": [
        "G3789"
      ],
      "strongs": "G3789",
      "morph": "robinson:N-VPM",
      "translation": "Serpents",
      "metadata": {},
      "gematria": {
        "standard": 785,
        "ordinal": 68,
        "reduced": 32
      }
    },
    {
      "position": 2,
      "text": "γεννήματα",
      "lemma": [
        "G1081"
      ],
      "strongs": "G1081",
      "morph": "robinson:N-VPN",
      "translation": "Offspring",
      "metadata": {},
      "gematria": {
        "standard": 458,
        "ordinal": 74,
        "reduced": 29
      }
    },
    {
      "position": 3,
      "text": "ἐχιδνῶν,",
      "lemma": [
        "G2191"
      ],
      "strongs": "G2191",
      "morph": "robinson:N-GPF",
      "translation": "of vipers!",
      "metadata": {},
      "gematria": {
        "standard": 1519,
        "ordinal": 90,
        "reduced": 36
      }
    },
    {
      "position": 4,
      "text": "πῶς",
      "lemma": [
        "G4459"
      ],
      "strongs": "G4459",
      "morph": "robinson:PRT-I",
      "translation": "How",
      "metadata": {},
      "gematria": {
        "standard": 1080,
        "ordinal": 58,
        "reduced": 22
      }
    },
    {
      "position": 5,
      "text": "φύγητε",
      "lemma": [
        "G5343"
      ],
      "strongs": "G5343",
      "morph": "robinson:V-2AAS-2P",
      "translation": "shall you escape",
      "metadata": {},
      "gematria": {
        "standard": 1216,
        "ordinal": 75,
        "reduced": 21
      }
    },
    {
      "position": 6,
      "text": "ἀπὸ",
      "lemma": [
        "G575"
      ],
      "strongs": "G575",
      "morph": "robinson:PREP",
      "translation": "from",
      "metadata": {},
      "gematria": {
        "standard": 151,
        "ordinal": 32,
        "reduced": 14
      }
    },
    {
      "position": 7,
      "text": "τῆς",
      "lemma": [
        "G3588"
      ],
      "strongs": "G3588",
      "morph": "robinson:T-GSF",
      "translation": "the",
      "metadata": {},
      "gematria": {
        "standard": 508,
        "ordinal": 44,
        "reduced": 17
      }
    },
    {
      "position": 8,
      "text": "κρίσεως",
      "lemma": [
        "G2920"
      ],
      "strongs": "G2920",
      "morph": "robinson:N-GSF",
      "translation": "sentence",
      "metadata": {},
      "gematria": {
        "standard": 1335,
        "ordinal": 101,
        "reduced": 47
      }
    },
    {
      "position": 9,
      "text": "τῆς",
      "lemma": [
        "G3588"
      ],
      "strongs": "G3588",
      "morph": "robinson:T-GSF",
      "translation": "<the>",
      "metadata": {},
      "gematria": {
        "standard": 508,
        "ordinal": 44,
        "reduced": 17
      }
    },
    {
      "position": 10,
      "text": "γεέννης;",
      "lemma": [
        "G1067"
      ],
      "strongs": "G1067",
      "morph": "robinson:N-GSF-T",
      "translation": "of hell?",
      "metadata": {},
      "gematria": {
        "standard": 321,
        "ordinal": 64,
        "reduced": 37
      }
    }
  ],
  "gematria": {
    "standard": 7881,
    "ordinal": 650,
    "reduced": 272
  }
}