{
  "text": "τότε ἀφίησιν αὐτὸν ὁ διάβολος, καὶ ἰδοὺ ἄγγελοι προσῆλθον καὶ διηκόνουν αὐτῷ.",
  "words": [
    {
      "position": 1,
      "text": "τότε",
      "lemma": [
        "G5119"
      ],
      "strongs": "G5119",
      "morph": "robinson:ADV",
      "translation": "Then",
      "metadata": {},
      "gematria": {
        "standard": 675,
        "ordinal": 58,
        "reduced": 13
      }
    },
    {
      "position": 2,
      "text": "ἀφίησιν",
      "lemma": null,
      "morph": null,
      "translation": "leaves",
      "metadata": {},
      "gematria": {
        "standard": 779,
        "ordinal": 78,
        "reduced": 42
      }
    },
    {
      "position": 3,
      "text": "αὐτὸν",
      "lemma": [
        "G846"
      ],
      "strongs": "G846",
      "morph": "robinson:P-ASM",
      "translation": "Him",
      "metadata": {},
      "gematria": {
        "standard": 821,
        "ordinal": 68,
        "reduced": 14
      }
    },
    {
      "position": 4,
      "text": "ὁ",
      "lemma": [
        "G3588"
      ],
      "strongs": "G3588",
      "morph": "robinson:T-NSM",
      "translation": "the",
      "metadata": {},
      "gematria": {
        "standard": 70,
        "ordinal": 15,
        "reduced": 6
      }
    },
    {
      "position": 5,
      "text": "διάβολος,",
      "lemma": [
        "G1228"
      ],
      "strongs": "G1228",
      "morph": "robinson:A-NSM",
      "translation": "devil,",
      "metadata": {},
      "gematria": {
        "standard": 387,
        "ordinal": 75,
        "reduced": 39
      }
    },
    {
      "position": 6,
      "text": "καὶ",
      "lemma": [
        "G2532"
      ],
      "strongs": "G2532",
      "morph": "robinson:CONJ",
      "translation": "and",
      "metadata": {},
      "gematria": {
        "standard": 31,
        "ordinal": 20,
        "reduced": 11
      }
    },
    {
      "position": 7,
      "text": "ἰδοὺ",
      "lemma": [
        "G2400"
      ],
      "strongs": "G2400",
      "morph": "robinson:INJ",
      "translation": "behold",
      "metadata": {},
      "gematria": {
        "standard": 484,
        "ordinal": 48,
        "reduced": 21
      }
    },
    {
      "position": 8,
      "text": "ἄγγελοι",
      "lemma": null,
      "morph": null,
      "translation": "angels",
      "metadata": {},
      "gematria": {
        "standard": 122,
        "ordinal": 47,
        "reduced": 29
      }
    },
    {
      "position": 9,
      "text": "προσῆλθον",
      "lemma": [
        "G4334"
      ],
      "strongs": "G4334",
      "morph": "robinson:V-2AAI-3P",
      "translation": "came",
      "metadata": {},
      "gematria": {
        "standard": 617,
        "ordinal": 120,
        "reduced": 57
      }
    },
    {
      "position": 10,
      "text": "καὶ",
      "lemma": [
        "G2532"
      ],
      "strongs": "G2532",
      "morph": "robinson:CONJ",
      "translation": "and",
      "metadata": {},
      "gematria": {
        "standard": 31,
        "ordinal": 20,
        "reduced": 11
      }
    },
    {
      "position": 11,
      "text": "διηκόνουν",
      "lemma": [
        "G1247"
      ],
      "strongs": "G1247",
      "morph": "robinson:V-IAI-3P",
      "translation": "they were ministering",
      "metadata": {},
      "gematria": {
        "standard": 682,
        "ordinal": 106,
        "reduced": 43
      }
    },
    {
      "position": 12,
      "text": "αὐτῷ.",
      "lemma": [
        "G846"
      ],
      "strongs": "G846",
      "morph": "robinson:P-DSM",
      "translation": "to Him.",
      "metadata": {},
      "gematria": {
        "standard": 1511,
        "ordinal": 73,
        "reduced": 19
      }
    }
  ],
  "gematria": {
    "standard": 6210,
    "ordinal": 728,
    "reduced": 305
  }
}