{
  "text": "ἀλλὰ διὰ τοῦτο ἠλεήθην, ἵνα ἐν ἐμοὶ πρώτῳ ἐνδείξηται Χριστὸς Ἰησοῦς τὴν ἅπασαν μακροθυμίαν πρὸς ὑποτύπωσιν τῶν μελλόντων πιστεύειν ἐπ᾽ αὐτῷ εἰς ζωὴν αἰώνιον.",
  "words": [
    {
      "position": 1,
      "text": "ἀλλὰ",
      "lemma": [
        "G235"
      ],
      "strongs": "G235",
      "morph": "robinson:CONJ",
      "translation": "But",
      "metadata": {},
      "gematria": {
        "standard": 62,
        "ordinal": 24,
        "reduced": 6
      }
    },
    {
      "position": 2,
      "text": "διὰ",
      "lemma": [
        "G1223"
      ],
      "strongs": "G1223",
      "morph": "robinson:PREP",
      "translation": "because of",
      "metadata": {},
      "gematria": {
        "standard": 15,
        "ordinal": 14,
        "reduced": 14
      }
    },
    {
      "position": 3,
      "text": "τοῦτο",
      "lemma": [
        "G3778"
      ],
      "strongs": "G3778",
      "morph": "robinson:D-ASN",
      "translation": "this",
      "metadata": {},
      "gematria": {
        "standard": 1140,
        "ordinal": 88,
        "reduced": 16
      }
    },
    {
      "position": 4,
      "text": "ἠλεήθην,",
      "lemma": [
        "G1653"
      ],
      "strongs": "G1653",
      "morph": "robinson:V-API-1S",
      "translation": "I was shown mercy,",
      "metadata": {},
      "gematria": {
        "standard": 118,
        "ordinal": 58,
        "reduced": 40
      }
    },
    {
      "position": 5,
      "text": "ἵνα",
      "lemma": [
        "G2443"
      ],
      "strongs": "G2443",
      "morph": "robinson:CONJ",
      "translation": "that",
      "metadata": {},
      "gematria": {
        "standard": 61,
        "ordinal": 23,
        "reduced": 14
      }
    },
    {
      "position": 6,
      "text": "ἐν",
      "lemma": [
        "G1722"
      ],
      "strongs": "G1722",
      "morph": "robinson:PREP",
      "translation": "in",
      "metadata": {},
      "gematria": {
        "standard": 55,
        "ordinal": 18,
        "reduced": 9
      }
    },
    {
      "position": 7,
      "text": "ἐμοὶ",
      "lemma": [
        "G1473"
      ],
      "strongs": "G1473",
      "morph": "robinson:P-1DS",
      "translation": "me myself",
      "metadata": {},
      "gematria": {
        "standard": 125,
        "ordinal": 41,
        "reduced": 23
      }
    },
    {
      "position": 8,
      "text": "πρώτῳ",
      "lemma": null,
      "morph": null,
      "translation": "[the] foremost",
      "metadata": {},
      "gematria": {
        "standard": 2090,
        "ordinal": 109,
        "reduced": 37
      }
    },
    {
      "position": 9,
      "text": "ἐνδείξηται",
      "lemma": [
        "G1731"
      ],
      "strongs": "G1731",
      "morph": "robinson:V-AMS-3S",
      "translation": "may display",
      "metadata": {},
      "gematria": {
        "standard": 453,
        "ordinal": 86,
        "reduced": 50
      }
    },
    {
      "position": 10,
      "text": "Χριστὸς",
      "lemma": [
        "G5547"
      ],
      "strongs": "G5547",
      "morph": "robinson:N-NSM-T",
      "translation": "Christ",
      "metadata": {},
      "gematria": {
        "standard": 1480,
        "ordinal": 118,
        "reduced": 46
      }
    },
    {
      "position": 11,
      "text": "Ἰησοῦς",
      "lemma": null,
      "morph": null,
      "translation": "Jesus",
      "metadata": {},
      "gematria": {
        "standard": 888,
        "ordinal": 87,
        "reduced": 42
      }
    },
    {
      "position": 12,
      "text": "τὴν",
      "lemma": [
        "G3588"
      ],
      "strongs": "G3588",
      "morph": "robinson:T-ASF",
      "translation": "<the>",
      "metadata": {},
      "gematria": {
        "standard": 358,
        "ordinal": 39,
        "reduced": 12
      }
    },
    {
      "position": 13,
      "text": "ἅπασαν",
      "lemma": [
        "G537"
      ],
      "strongs": "G537",
      "morph": "robinson:A-ASF",
      "translation": "[his] perfect",
      "metadata": {},
      "gematria": {
        "standard": 333,
        "ordinal": 50,
        "reduced": 23
      }
    },
    {
      "position": 14,
      "text": "μακροθυμίαν",
      "lemma": [
        "G3115"
      ],
      "strongs": "G3115",
      "morph": "robinson:N-ASF",
      "translation": "patience",
      "metadata": {},
      "gematria": {
        "standard": 741,
        "ordinal": 118,
        "reduced": 46
      }
    },
    {
      "position": 15,
      "text": "πρὸς",
      "lemma": [
        "G4314"
      ],
      "strongs": "G4314",
      "morph": "robinson:PREP",
      "translation": "as",
      "metadata": {},
      "gematria": {
        "standard": 450,
        "ordinal": 66,
        "reduced": 30
      }
    },
    {
      "position": 16,
      "text": "ὑποτύπωσιν",
      "lemma": [
        "G5296"
      ],
      "strongs": "G5296",
      "morph": "robinson:N-ASF",
      "translation": "a pattern",
      "metadata": {},
      "gematria": {
        "standard": 2390,
        "ordinal": 170,
        "reduced": 53
      }
    },
    {
      "position": 17,
      "text": "τῶν",
      "lemma": [
        "G3588"
      ],
      "strongs": "G3588",
      "morph": "robinson:T-GPM",
      "translation": "for those",
      "metadata": {},
      "gematria": {
        "standard": 1150,
        "ordinal": 56,
        "reduced": 11
      }
    },
    {
      "position": 18,
      "text": "μελλόντων",
      "lemma": [
        "G3195"
      ],
      "strongs": "G3195",
      "morph": "robinson:V-PAP-GPM",
      "translation": "being about",
      "metadata": {},
      "gematria": {
        "standard": 1375,
        "ordinal": 123,
        "reduced": 33
      }
    },
    {
      "position": 19,
      "text": "πιστεύειν",
      "lemma": [
        "G4100"
      ],
      "strongs": "G4100",
      "morph": "robinson:V-PAN",
      "translation": "to believe",
      "metadata": {},
      "gematria": {
        "standard": 1060,
        "ordinal": 114,
        "reduced": 51
      }
    },
    {
      "position": 20,
      "text": "ἐπ᾽",
      "lemma": [
        "G1909"
      ],
      "strongs": "G1909",
      "morph": "robinson:PREP",
      "translation": "on",
      "metadata": {},
      "gematria": {
        "standard": 85,
        "ordinal": 21,
        "reduced": 12
      }
    },
    {
      "position": 21,
      "text": "αὐτῷ",
      "lemma": [
        "G846"
      ],
      "strongs": "G846",
      "morph": "robinson:P-DSM",
      "translation": "Him",
      "metadata": {},
      "gematria": {
        "standard": 1511,
        "ordinal": 73,
        "reduced": 19
      }
    },
    {
      "position": 22,
      "text": "εἰς",
      "lemma": [
        "G1519"
      ],
      "strongs": "G1519",
      "morph": "robinson:PREP",
      "translation": "to",
      "metadata": {},
      "gematria": {
        "standard": 215,
        "ordinal": 32,
        "reduced": 23
      }
    },
    {
      "position": 23,
      "text": "ζωὴν",
      "lemma": [
        "G2222"
      ],
      "strongs": "G2222",
      "morph": "robinson:N-ASF",
      "translation": "life",
      "metadata": {},
      "gematria": {
        "standard": 865,
        "ordinal": 50,
        "reduced": 23
      }
    },
    {
      "position": 24,
      "text": "αἰώνιον.",
      "lemma": [
        "G166"
      ],
      "strongs": "G166",
      "morph": "robinson:A-ASF",
      "translation": "eternal.",
      "metadata": {},
      "gematria": {
        "standard": 991,
        "ordinal": 84,
        "reduced": 39
      }
    }
  ],
  "gematria": {
    "standard": 18011,
    "ordinal": 1662,
    "reduced": 672
  }
}