{
  "text": "καὶ ὑπὲρ ἐμοῦ, ἵνα μοι λόγος ἐν ἀνοίξει τοῦ στόματός μου ἐν παρρησίᾳ γνωρίσαι τὸ μυστήριον τοῦ εὐαγγελίου,",
  "words": [
    {
      "position": 1,
      "text": "καὶ",
      "lemma": [
        "G2532"
      ],
      "strongs": "G2532",
      "morph": "robinson:CONJ",
      "translation": "and also",
      "metadata": {},
      "gematria": {
        "standard": 31,
        "ordinal": 20,
        "reduced": 11
      }
    },
    {
      "position": 2,
      "text": "ὑπὲρ",
      "lemma": [
        "G5228"
      ],
      "strongs": "G5228",
      "morph": "robinson:PREP",
      "translation": "for",
      "metadata": {},
      "gematria": {
        "standard": 585,
        "ordinal": 58,
        "reduced": 22
      }
    },
    {
      "position": 3,
      "text": "ἐμοῦ,",
      "lemma": [
        "G1473"
      ],
      "strongs": "G1473",
      "morph": "robinson:S-1SGSN",
      "translation": "me,",
      "metadata": {},
      "gematria": {
        "standard": 515,
        "ordinal": 52,
        "reduced": 16
      }
    },
    {
      "position": 4,
      "text": "ἵνα",
      "lemma": [
        "G2443"
      ],
      "strongs": "G2443",
      "morph": "robinson:CONJ",
      "translation": "that",
      "metadata": {},
      "gematria": {
        "standard": 61,
        "ordinal": 23,
        "reduced": 14
      }
    },
    {
      "position": 5,
      "text": "μοι",
      "lemma": [
        "G3165"
      ],
      "strongs": "G3165",
      "morph": "robinson:P-1DS",
      "translation": "to me",
      "metadata": {},
      "gematria": {
        "standard": 120,
        "ordinal": 36,
        "reduced": 18
      }
    },
    {
      "position": 6,
      "text": "λόγος",
      "lemma": [
        "G3056"
      ],
      "strongs": "G3056",
      "morph": "robinson:N-NSM",
      "translation": "divine utterance",
      "metadata": {},
      "gematria": {
        "standard": 373,
        "ordinal": 62,
        "reduced": 26
      }
    },
    {
      "position": 7,
      "text": "ἐν",
      "lemma": [
        "G1722"
      ],
      "strongs": "G1722",
      "morph": "robinson:PREP",
      "translation": "in",
      "metadata": {},
      "gematria": {
        "standard": 55,
        "ordinal": 18,
        "reduced": 9
      }
    },
    {
      "position": 8,
      "text": "ἀνοίξει",
      "lemma": [
        "G457"
      ],
      "strongs": "G457",
      "morph": "robinson:N-DSF",
      "translation": "[the] opening",
      "metadata": {},
      "gematria": {
        "standard": 206,
        "ordinal": 66,
        "reduced": 39
      }
    },
    {
      "position": 9,
      "text": "τοῦ",
      "lemma": [
        "G3588"
      ],
      "strongs": "G3588",
      "morph": "robinson:T-GSN",
      "translation": "of the",
      "metadata": {},
      "gematria": {
        "standard": 770,
        "ordinal": 54,
        "reduced": 9
      }
    },
    {
      "position": 10,
      "text": "στόματός",
      "lemma": [
        "G4750"
      ],
      "strongs": "G4750",
      "morph": "robinson:N-GSN",
      "translation": "mouth",
      "metadata": {},
      "gematria": {
        "standard": 1181,
        "ordinal": 117,
        "reduced": 36
      }
    },
    {
      "position": 11,
      "text": "μου",
      "lemma": [
        "G3165"
      ],
      "strongs": "G3165",
      "morph": "robinson:P-1GS",
      "translation": "of mine",
      "metadata": {},
      "gematria": {
        "standard": 510,
        "ordinal": 47,
        "reduced": 11
      }
    },
    {
      "position": 12,
      "text": "ἐν",
      "lemma": [
        "G1722"
      ],
      "strongs": "G1722",
      "morph": "robinson:PREP",
      "translation": "with",
      "metadata": {},
      "gematria": {
        "standard": 55,
        "ordinal": 18,
        "reduced": 9
      }
    },
    {
      "position": 13,
      "text": "παρρησίᾳ",
      "lemma": [
        "G3954"
      ],
      "strongs": "G3954",
      "morph": "robinson:N-DSF",
      "translation": "boldness",
      "metadata": {},
      "gematria": {
        "standard": 510,
        "ordinal": 95,
        "reduced": 59
      }
    },
    {
      "position": 14,
      "text": "γνωρίσαι",
      "lemma": [
        "G1107"
      ],
      "strongs": "G1107",
      "morph": "robinson:V-AAN",
      "translation": "to make known",
      "metadata": {},
      "gematria": {
        "standard": 1174,
        "ordinal": 94,
        "reduced": 49
      }
    },
    {
      "position": 15,
      "text": "τὸ",
      "lemma": [
        "G3588"
      ],
      "strongs": "G3588",
      "morph": "robinson:T-ASN",
      "translation": "the",
      "metadata": {},
      "gematria": {
        "standard": 370,
        "ordinal": 34,
        "reduced": 7
      }
    },
    {
      "position": 16,
      "text": "μυστήριον",
      "lemma": [
        "G3466"
      ],
      "strongs": "G3466",
      "morph": "robinson:N-ASN",
      "translation": "mystery",
      "metadata": {},
      "gematria": {
        "standard": 1178,
        "ordinal": 130,
        "reduced": 49
      }
    },
    {
      "position": 17,
      "text": "τοῦ",
      "lemma": [
        "G3588"
      ],
      "strongs": "G3588",
      "morph": "robinson:T-GSN",
      "translation": "of the",
      "metadata": {},
      "gematria": {
        "standard": 770,
        "ordinal": 54,
        "reduced": 9
      }
    },
    {
      "position": 18,
      "text": "εὐαγγελίου,",
      "lemma": [
        "G2098"
      ],
      "strongs": "G2098",
      "morph": "robinson:N-GSN",
      "translation": "gospel,",
      "metadata": {},
      "gematria": {
        "standard": 927,
        "ordinal": 92,
        "reduced": 38
      }
    }
  ],
  "gematria": {
    "standard": 9391,
    "ordinal": 1070,
    "reduced": 431
  }
}