{
  "text": "πάντα γὰρ ὑπέταξεν ὑπὸ τοὺς πόδας αὐτοῦ· ὅταν δὲ εἴπῃ ὅτι πάντα ὑποτέτακται, δῆλον ὅτι ἐκτὸς τοῦ ὑποτάξαντος αὐτῷ τὰ πάντα·",
  "words": [
    {
      "position": 1,
      "text": "πάντα",
      "lemma": [
        "G3956"
      ],
      "strongs": "G3956",
      "morph": "robinson:A-APN",
      "translation": "All things",
      "metadata": {},
      "gematria": {
        "standard": 432,
        "ordinal": 50,
        "reduced": 14
      }
    },
    {
      "position": 2,
      "text": "γὰρ",
      "lemma": [
        "G1063"
      ],
      "strongs": "G1063",
      "morph": "robinson:CONJ",
      "translation": "for",
      "metadata": {},
      "gematria": {
        "standard": 104,
        "ordinal": 21,
        "reduced": 12
      }
    },
    {
      "position": 3,
      "text": "ὑπέταξεν",
      "lemma": [
        "G5293"
      ],
      "strongs": "G5293",
      "morph": "robinson:V-2AAI-3S",
      "translation": "He has put in subjection",
      "metadata": {},
      "gematria": {
        "standard": 901,
        "ordinal": 93,
        "reduced": 30
      }
    },
    {
      "position": 4,
      "text": "ὑπὸ",
      "lemma": null,
      "morph": null,
      "translation": "under",
      "metadata": {},
      "gematria": {
        "standard": 550,
        "ordinal": 51,
        "reduced": 15
      }
    },
    {
      "position": 5,
      "text": "τοὺς",
      "lemma": [
        "G3588"
      ],
      "strongs": "G3588",
      "morph": "robinson:T-APM",
      "translation": "the",
      "metadata": {},
      "gematria": {
        "standard": 970,
        "ordinal": 72,
        "reduced": 18
      }
    },
    {
      "position": 6,
      "text": "πόδας",
      "lemma": [
        "G4228"
      ],
      "strongs": "G4228",
      "morph": "robinson:N-APM",
      "translation": "feet",
      "metadata": {},
      "gematria": {
        "standard": 355,
        "ordinal": 54,
        "reduced": 27
      }
    },
    {
      "position": 7,
      "text": "αὐτοῦ·",
      "lemma": [
        "G846"
      ],
      "strongs": "G846",
      "morph": "robinson:P-GSM",
      "translation": "of Him;",
      "metadata": {},
      "gematria": {
        "standard": 1171,
        "ordinal": 75,
        "reduced": 12
      }
    },
    {
      "position": 8,
      "text": "ὅταν",
      "lemma": [
        "G3752"
      ],
      "strongs": "G3752",
      "morph": "robinson:CONJ",
      "translation": "When",
      "metadata": {},
      "gematria": {
        "standard": 421,
        "ordinal": 48,
        "reduced": 12
      }
    },
    {
      "position": 9,
      "text": "δὲ",
      "lemma": [
        "G1161"
      ],
      "strongs": "G1161",
      "morph": "robinson:CONJ",
      "translation": "however",
      "metadata": {},
      "gematria": {
        "standard": 9,
        "ordinal": 9,
        "reduced": 9
      }
    },
    {
      "position": 10,
      "text": "εἴπῃ",
      "lemma": [
        "G2036"
      ],
      "strongs": "G2036",
      "morph": "robinson:V-2AAS-3S",
      "translation": "it may be said",
      "metadata": {},
      "gematria": {
        "standard": 113,
        "ordinal": 46,
        "reduced": 37
      }
    },
    {
      "position": 11,
      "text": "ὅτι",
      "lemma": null,
      "morph": null,
      "translation": "that",
      "metadata": {},
      "gematria": {
        "standard": 380,
        "ordinal": 43,
        "reduced": 16
      }
    },
    {
      "position": 12,
      "text": "πάντα",
      "lemma": [
        "G3956"
      ],
      "strongs": "G3956",
      "morph": "robinson:A-NPN",
      "translation": "all things",
      "metadata": {},
      "gematria": {
        "standard": 432,
        "ordinal": 50,
        "reduced": 14
      }
    },
    {
      "position": 13,
      "text": "ὑποτέτακται,",
      "lemma": [
        "G5293"
      ],
      "strongs": "G5293",
      "morph": "robinson:V-RPI-3S",
      "translation": "have been put in subjection,",
      "metadata": {},
      "gematria": {
        "standard": 1487,
        "ordinal": 134,
        "reduced": 35
      }
    },
    {
      "position": 14,
      "text": "δῆλον",
      "lemma": [
        "G1212"
      ],
      "strongs": "G1212",
      "morph": "robinson:A-NSN",
      "translation": "[it is] evident",
      "metadata": {},
      "gematria": {
        "standard": 162,
        "ordinal": 50,
        "reduced": 23
      }
    },
    {
      "position": 15,
      "text": "ὅτι",
      "lemma": null,
      "morph": null,
      "translation": "that",
      "metadata": {},
      "gematria": {
        "standard": 380,
        "ordinal": 43,
        "reduced": 16
      }
    },
    {
      "position": 16,
      "text": "ἐκτὸς",
      "lemma": [
        "G1622"
      ],
      "strongs": "G1622",
      "morph": "robinson:PREP",
      "translation": "[is] excepted",
      "metadata": {},
      "gematria": {
        "standard": 595,
        "ordinal": 67,
        "reduced": 22
      }
    },
    {
      "position": 17,
      "text": "τοῦ",
      "lemma": [
        "G3588"
      ],
      "strongs": "G3588",
      "morph": "robinson:T-GSM",
      "translation": "the [One who]",
      "metadata": {},
      "gematria": {
        "standard": 770,
        "ordinal": 54,
        "reduced": 9
      }
    },
    {
      "position": 18,
      "text": "ὑποτάξαντος",
      "lemma": [
        "G5293"
      ],
      "strongs": "G5293",
      "morph": "robinson:V-2AAP-GSM",
      "translation": "having put in subjection",
      "metadata": {},
      "gematria": {
        "standard": 1532,
        "ordinal": 151,
        "reduced": 43
      }
    },
    {
      "position": 19,
      "text": "αὐτῷ",
      "lemma": [
        "G846"
      ],
      "strongs": "G846",
      "morph": "robinson:P-DSM",
      "translation": "to Him",
      "metadata": {},
      "gematria": {
        "standard": 1511,
        "ordinal": 73,
        "reduced": 19
      }
    },
    {
      "position": 20,
      "text": "τὰ",
      "lemma": [
        "G3588"
      ],
      "strongs": "G3588",
      "morph": "robinson:T-APN",
      "translation": "<the>",
      "metadata": {},
      "gematria": {
        "standard": 301,
        "ordinal": 20,
        "reduced": 2
      }
    },
    {
      "position": 21,
      "text": "πάντα·",
      "lemma": [
        "G3956"
      ],
      "strongs": "G3956",
      "morph": "robinson:A-APN",
      "translation": "all things;",
      "metadata": {},
      "gematria": {
        "standard": 432,
        "ordinal": 50,
        "reduced": 14
      }
    }
  ],
  "gematria": {
    "standard": 13008,
    "ordinal": 1254,
    "reduced": 399
  }
}