{
  "text": "γνωστὰ ἀπ᾽ αἰῶνος ἐστιν τῷ θεῷ πάντα τὰ ἔργα αὐτοῦ.",
  "words": [
    {
      "position": 1,
      "text": "γνωστὰ",
      "lemma": [
        "G1110"
      ],
      "strongs": "G1110",
      "morph": "robinson:A-APN",
      "translation": "known",
      "metadata": {},
      "gematria": {
        "standard": 1354,
        "ordinal": 78,
        "reduced": 24
      }
    },
    {
      "position": 2,
      "text": "ἀπ᾽",
      "lemma": [
        "G575"
      ],
      "strongs": "G575",
      "morph": "robinson:PREP",
      "translation": "from",
      "metadata": {},
      "gematria": {
        "standard": 81,
        "ordinal": 17,
        "reduced": 8
      }
    },
    {
      "position": 3,
      "text": "αἰῶνος",
      "lemma": null,
      "morph": null,
      "translation": "eternity’",
      "metadata": {},
      "gematria": {
        "standard": 1131,
        "ordinal": 80,
        "reduced": 35
      }
    },
    {
      "position": 4,
      "text": "ἐστιν",
      "lemma": [
        "G1510"
      ],
      "strongs": "G1510",
      "morph": "robinson:V-PAI-3S",
      "translation": "is",
      "metadata": {},
      "gematria": {
        "standard": 565,
        "ordinal": 64,
        "reduced": 28
      }
    },
    {
      "position": 5,
      "text": "τῷ",
      "lemma": [
        "G3588"
      ],
      "strongs": "G3588",
      "morph": "robinson:T-DSM",
      "translation": "<the>",
      "metadata": {},
      "gematria": {
        "standard": 1110,
        "ordinal": 52,
        "reduced": 16
      }
    },
    {
      "position": 6,
      "text": "θεῷ",
      "lemma": [
        "G2316"
      ],
      "strongs": "G2316",
      "morph": "robinson:N-DSM-T",
      "translation": "to God",
      "metadata": {},
      "gematria": {
        "standard": 824,
        "ordinal": 46,
        "reduced": 28
      }
    },
    {
      "position": 7,
      "text": "πάντα",
      "lemma": [
        "G3956"
      ],
      "strongs": "G3956",
      "morph": "robinson:A-NPN",
      "translation": "all",
      "metadata": {},
      "gematria": {
        "standard": 432,
        "ordinal": 50,
        "reduced": 14
      }
    },
    {
      "position": 8,
      "text": "τὰ",
      "lemma": [
        "G3588"
      ],
      "strongs": "G3588",
      "morph": "robinson:T-NPN",
      "translation": "the",
      "metadata": {},
      "gematria": {
        "standard": 301,
        "ordinal": 20,
        "reduced": 2
      }
    },
    {
      "position": 9,
      "text": "ἔργα",
      "lemma": [
        "G2041"
      ],
      "strongs": "G2041",
      "morph": "robinson:N-NPN",
      "translation": "works",
      "metadata": {},
      "gematria": {
        "standard": 109,
        "ordinal": 26,
        "reduced": 17
      }
    },
    {
      "position": 10,
      "text": "αὐτοῦ.",
      "lemma": [
        "G846"
      ],
      "strongs": "G846",
      "morph": "robinson:P-GSM",
      "translation": "of him.",
      "metadata": {},
      "gematria": {
        "standard": 1171,
        "ordinal": 75,
        "reduced": 12
      }
    }
  ],
  "gematria": {
    "standard": 7078,
    "ordinal": 508,
    "reduced": 184
  }
}