{
  "text": "καθὼς τὸ μαρτύριον τοῦ Χριστοῦ ἐβεβαιώθη ἐν ὑμῖν,",
  "words": [
    {
      "position": 1,
      "text": "καθὼς",
      "lemma": [
        "G2531"
      ],
      "strongs": "G2531",
      "morph": "robinson:CONJ",
      "translation": "even as",
      "metadata": {},
      "gematria": {
        "standard": 1030,
        "ordinal": 61,
        "reduced": 25
      }
    },
    {
      "position": 2,
      "text": "τὸ",
      "lemma": [
        "G3588"
      ],
      "strongs": "G3588",
      "morph": "robinson:T-NSN",
      "translation": "the",
      "metadata": {},
      "gematria": {
        "standard": 370,
        "ordinal": 34,
        "reduced": 7
      }
    },
    {
      "position": 3,
      "text": "μαρτύριον",
      "lemma": [
        "G3142"
      ],
      "strongs": "G3142",
      "morph": "robinson:N-NSN",
      "translation": "testimony",
      "metadata": {},
      "gematria": {
        "standard": 1071,
        "ordinal": 123,
        "reduced": 42
      }
    },
    {
      "position": 4,
      "text": "τοῦ",
      "lemma": [
        "G3588"
      ],
      "strongs": "G3588",
      "morph": "robinson:T-GSM",
      "translation": "<the>",
      "metadata": {},
      "gematria": {
        "standard": 770,
        "ordinal": 54,
        "reduced": 9
      }
    },
    {
      "position": 5,
      "text": "Χριστοῦ",
      "lemma": [
        "G5547"
      ],
      "strongs": "G5547",
      "morph": "robinson:N-GSM-T",
      "translation": "about Christ",
      "metadata": {},
      "gematria": {
        "standard": 1680,
        "ordinal": 120,
        "reduced": 39
      }
    },
    {
      "position": 6,
      "text": "ἐβεβαιώθη",
      "lemma": [
        "G950"
      ],
      "strongs": "G950",
      "morph": "robinson:V-API-3S",
      "translation": "was confirmed",
      "metadata": {},
      "gematria": {
        "standard": 842,
        "ordinal": 63,
        "reduced": 45
      }
    },
    {
      "position": 7,
      "text": "ἐν",
      "lemma": [
        "G1722"
      ],
      "strongs": "G1722",
      "morph": "robinson:PREP",
      "translation": "in",
      "metadata": {},
      "gematria": {
        "standard": 55,
        "ordinal": 18,
        "reduced": 9
      }
    },
    {
      "position": 8,
      "text": "ὑμῖν,",
      "lemma": [
        "G4771"
      ],
      "strongs": "G4771",
      "morph": "robinson:P-2DP",
      "translation": "you,",
      "metadata": {},
      "gematria": {
        "standard": 500,
        "ordinal": 54,
        "reduced": 18
      }
    }
  ],
  "gematria": {
    "standard": 6318,
    "ordinal": 527,
    "reduced": 194
  }
}