{
  "text": "τοῦτο ἐν ὑμῖν ὃ καὶ ἐν Χριστῷ Ἰησοῦ,",
  "words": [
    {
      "position": 1,
      "text": "τοῦτο",
      "lemma": [
        "G3778"
      ],
      "strongs": "G3778",
      "morph": "robinson:D-ASN",
      "translation": "This",
      "metadata": {},
      "gematria": {
        "standard": 1140,
        "ordinal": 88,
        "reduced": 16
      }
    },
    {
      "position": 2,
      "text": "ἐν",
      "lemma": [
        "G1722"
      ],
      "strongs": "G1722",
      "morph": "robinson:PREP",
      "translation": "in",
      "metadata": {},
      "gematria": {
        "standard": 55,
        "ordinal": 18,
        "reduced": 9
      }
    },
    {
      "position": 3,
      "text": "ὑμῖν",
      "lemma": [
        "G4771"
      ],
      "strongs": "G4771",
      "morph": "robinson:P-2DP",
      "translation": "you",
      "metadata": {},
      "gematria": {
        "standard": 500,
        "ordinal": 54,
        "reduced": 18
      }
    },
    {
      "position": 4,
      "text": "ὃ",
      "lemma": [
        "G3739"
      ],
      "strongs": "G3739",
      "morph": "robinson:R-NSN",
      "translation": "which",
      "metadata": {},
      "gematria": {
        "standard": 70,
        "ordinal": 15,
        "reduced": 6
      }
    },
    {
      "position": 5,
      "text": "καὶ",
      "lemma": [
        "G2532"
      ],
      "strongs": "G2532",
      "morph": "robinson:CONJ",
      "translation": "also",
      "metadata": {},
      "gematria": {
        "standard": 31,
        "ordinal": 20,
        "reduced": 11
      }
    },
    {
      "position": 6,
      "text": "ἐν",
      "lemma": [
        "G1722"
      ],
      "strongs": "G1722",
      "morph": "robinson:PREP",
      "translation": "in",
      "metadata": {},
      "gematria": {
        "standard": 55,
        "ordinal": 18,
        "reduced": 9
      }
    },
    {
      "position": 7,
      "text": "Χριστῷ",
      "lemma": [
        "G5547"
      ],
      "strongs": "G5547",
      "morph": "robinson:N-DSM-T",
      "translation": "Christ",
      "metadata": {},
      "gematria": {
        "standard": 2020,
        "ordinal": 118,
        "reduced": 46
      }
    },
    {
      "position": 8,
      "text": "Ἰησοῦ,",
      "lemma": [
        "G2424"
      ],
      "strongs": "G2424",
      "morph": "robinson:N-DSM-P",
      "translation": "Jesus [was]:",
      "metadata": {},
      "gematria": {
        "standard": 688,
        "ordinal": 69,
        "reduced": 33
      }
    }
  ],
  "gematria": {
    "standard": 4559,
    "ordinal": 400,
    "reduced": 148
  }
}