{
  "text": "Ἤδη δὲ τῆς ἑορτῆς μεσούσης ἀνέβη Ἰησοῦς εἰς τὸ ἱερὸν καὶ ἐδίδασκεν.",
  "words": [
    {
      "position": 1,
      "text": "Ἤδη",
      "lemma": [
        "G2235"
      ],
      "strongs": "G2235",
      "morph": "robinson:ADV",
      "translation": "Now",
      "metadata": {},
      "gematria": {
        "standard": 20,
        "ordinal": 18,
        "reduced": 18
      }
    },
    {
      "position": 2,
      "text": "δὲ",
      "lemma": [
        "G1161"
      ],
      "strongs": "G1161",
      "morph": "robinson:CONJ",
      "translation": "also",
      "metadata": {},
      "gematria": {
        "standard": 9,
        "ordinal": 9,
        "reduced": 9
      }
    },
    {
      "position": 3,
      "text": "τῆς",
      "lemma": [
        "G3588"
      ],
      "strongs": "G3588",
      "morph": "robinson:T-GSF",
      "translation": "of the",
      "metadata": {},
      "gematria": {
        "standard": 508,
        "ordinal": 44,
        "reduced": 17
      }
    },
    {
      "position": 4,
      "text": "ἑορτῆς",
      "lemma": [
        "G1859"
      ],
      "strongs": "G1859",
      "morph": "robinson:N-GSF",
      "translation": "feast",
      "metadata": {},
      "gematria": {
        "standard": 683,
        "ordinal": 81,
        "reduced": 36
      }
    },
    {
      "position": 5,
      "text": "μεσούσης",
      "lemma": [
        "G3322"
      ],
      "strongs": "G3322",
      "morph": "robinson:V-PAP-GSF",
      "translation": "being in the middle",
      "metadata": {},
      "gematria": {
        "standard": 1123,
        "ordinal": 113,
        "reduced": 50
      }
    },
    {
      "position": 6,
      "text": "ἀνέβη",
      "lemma": [
        "G305"
      ],
      "strongs": "G305",
      "morph": "robinson:V-2AAI-3S",
      "translation": "went up",
      "metadata": {},
      "gematria": {
        "standard": 66,
        "ordinal": 28,
        "reduced": 19
      }
    },
    {
      "position": 7,
      "text": "Ἰησοῦς",
      "lemma": null,
      "morph": null,
      "translation": "Jesus",
      "metadata": {},
      "gematria": {
        "standard": 888,
        "ordinal": 87,
        "reduced": 42
      }
    },
    {
      "position": 8,
      "text": "εἰς",
      "lemma": [
        "G1519"
      ],
      "strongs": "G1519",
      "morph": "robinson:PREP",
      "translation": "into",
      "metadata": {},
      "gematria": {
        "standard": 215,
        "ordinal": 32,
        "reduced": 23
      }
    },
    {
      "position": 9,
      "text": "τὸ",
      "lemma": [
        "G3588"
      ],
      "strongs": "G3588",
      "morph": "robinson:T-ASN",
      "translation": "the",
      "metadata": {},
      "gematria": {
        "standard": 370,
        "ordinal": 34,
        "reduced": 7
      }
    },
    {
      "position": 10,
      "text": "ἱερὸν",
      "lemma": [
        "G2411"
      ],
      "strongs": "G2411",
      "morph": "robinson:N-ASN",
      "translation": "temple",
      "metadata": {},
      "gematria": {
        "standard": 235,
        "ordinal": 59,
        "reduced": 32
      }
    },
    {
      "position": 11,
      "text": "καὶ",
      "lemma": [
        "G2532"
      ],
      "strongs": "G2532",
      "morph": "robinson:CONJ",
      "translation": "and",
      "metadata": {},
      "gematria": {
        "standard": 31,
        "ordinal": 20,
        "reduced": 11
      }
    },
    {
      "position": 12,
      "text": "ἐδίδασκεν.",
      "lemma": [
        "G1321"
      ],
      "strongs": "G1321",
      "morph": "robinson:V-IAI-3S",
      "translation": "was teaching.",
      "metadata": {},
      "gematria": {
        "standard": 299,
        "ordinal": 69,
        "reduced": 42
      }
    }
  ],
  "gematria": {
    "standard": 4447,
    "ordinal": 594,
    "reduced": 306
  }
}